insightface_paddle/LICENSE
insightface_paddle/MANIFEST.in
insightface_paddle/README.md
insightface_paddle/README_en.md
insightface_paddle/SourceHanSansCN-Medium.otf
insightface_paddle/__init__.py
insightface_paddle/check_invalid_link.py
insightface_paddle/insightface_paddle.py
insightface_paddle/requirements.txt
insightface_paddle/insightface_paddle.egg-info/PKG-INFO
insightface_paddle/insightface_paddle.egg-info/SOURCES.txt
insightface_paddle/insightface_paddle.egg-info/dependency_links.txt
insightface_paddle/insightface_paddle.egg-info/entry_points.txt
insightface_paddle/insightface_paddle.egg-info/requires.txt
insightface_paddle/insightface_paddle.egg-info/top_level.txt
insightface_paddle-2.0.0.dist-info/LICENSE
insightface_paddle-2.0.0.dist-info/METADATA
insightface_paddle-2.0.0.dist-info/WHEEL
insightface_paddle-2.0.0.dist-info/entry_points.txt
insightface_paddle-2.0.0.dist-info/top_level.txt
insightface_paddle-2.0.0.dist-info/RECORD
