Metadata-Version: 2.1
Name: insightface-paddle
Version: 2.0.0
Summary: A toolkit for face detection and recognition powered by PaddlePaddle.
Home-page: https://github.com/littletomatodonkey/insight-face-paddle
Author: Baidu
Author-email: dazhiningsibuqu@163.com
License: Apache License 2.0
Download-URL: https://github.com/littletomatodonkey/insight-face-paddle.git
Keywords: insight face,Arcface,BlazeFace,MobileFace,face detection,face recognition,PaddlePaddle
Platform: UNKNOWN
Classifier: Intended Audience :: Developers
Classifier: Operating System :: OS Independent
Classifier: Natural Language :: Chinese (Simplified)
Classifier: Programming Language :: Python :: 3
Classifier: Programming Language :: Python :: 3.2
Classifier: Programming Language :: Python :: 3.3
Classifier: Programming Language :: Python :: 3.4
Classifier: Programming Language :: Python :: 3.5
Classifier: Programming Language :: Python :: 3.6
Classifier: Programming Language :: Python :: 3.7
Classifier: Topic :: Utilities
Requires-Dist: requests
Requires-Dist: prettytable
Requires-Dist: tqdm
Requires-Dist: Pillow
Requires-Dist: scikit-learn (==0.23.2)
Requires-Dist: opencv-python (==4.4.0.46)
Requires-Dist: numpy
